Doodke/CancelShutdown.py
Doodke/CustomPrint.py
Doodke/Help.py
Doodke/Math.py
Doodke/School.py
Doodke/Secret.py
Doodke/Shutdown.py
Doodke/UwU.py
Doodke/__init__.py
Doodke-0.1.3.dist-info/LICENSE
Doodke-0.1.3.dist-info/METADATA
Doodke-0.1.3.dist-info/WHEEL
Doodke-0.1.3.dist-info/top_level.txt
Doodke-0.1.3.dist-info/RECORD
