Metadata-Version: 2.1
Name: Doodke
Version: 0.1.3
Summary: A small test package
Home-page: https://doodke.xyz#nothing_for_now
Author: David
Author-email: david@doodke.xyz
License: UNKNOWN
Project-URL: Bug Tracker, https://doodke.xyz#nothing_for_now
Platform: UNKNOWN
Classifier: Programming Language :: Python :: 3
Classifier: License :: OSI Approved :: MIT License
Classifier: Operating System :: OS Independent
Requires-Python: >=3.6
License-File: LICENSE
